barchartFetcher/__init__.py
barchartFetcher/main/Analysts.py
barchartFetcher/main/Company.py
barchartFetcher/main/Financials.py
barchartFetcher/main/Options.py
barchartFetcher/main/OptionsStrategies.py
barchartFetcher/main/Quotes.py
barchartFetcher/main/Symbol.py
barchartFetcher/main/Technicals.py
barchartFetcher/main/__init__.py
barchartFetcher/utils/__init__.py
barchartFetcher/utils/query_async_dicts.py
barchartFetcher/utils/query_auth_class.py
barchartFetcher/utils/query_functions.py
barchartFetcher/utils/query_manager.py
barchartFetcher/utils/html_parser_functions/__init__.py
barchartFetcher/utils/html_parser_functions/financial_table_parser.py
barchartFetcher/utils/sync_query_functions/__init__.py
barchartFetcher/utils/sync_query_functions/analysts/__init__.py
barchartFetcher/utils/sync_query_functions/analysts/earnings_estimates.py
barchartFetcher/utils/sync_query_functions/analysts/ratings.py
barchartFetcher/utils/sync_query_functions/company/__init__.py
barchartFetcher/utils/sync_query_functions/company/competitors.py
barchartFetcher/utils/sync_query_functions/company/insider_trades.py
barchartFetcher/utils/sync_query_functions/company/key_statistics.py
barchartFetcher/utils/sync_query_functions/company/sec_filings.py
barchartFetcher/utils/sync_query_functions/financials/__init__.py
barchartFetcher/utils/sync_query_functions/financials/balance_sheet.py
barchartFetcher/utils/sync_query_functions/financials/cash_flow.py
barchartFetcher/utils/sync_query_functions/financials/income_statement.py
barchartFetcher/utils/sync_query_functions/financials/summary.py
barchartFetcher/utils/sync_query_functions/options/__init__.py
barchartFetcher/utils/sync_query_functions/options/expected_move.py
barchartFetcher/utils/sync_query_functions/options/expirations.py
barchartFetcher/utils/sync_query_functions/options/flow.py
barchartFetcher/utils/sync_query_functions/options/gamma_exposure.py
barchartFetcher/utils/sync_query_functions/options/max_pain_vol_skew.py
barchartfetcher-1.1.0.dist-info/licenses/LICENSE
barchartfetcher-1.1.0.dist-info/METADATA
barchartfetcher-1.1.0.dist-info/WHEEL
barchartfetcher-1.1.0.dist-info/top_level.txt
barchartfetcher-1.1.0.dist-info/RECORD
