Metadata-Version: 2.4
Name: barchartFetcher
Version: 1.1.0
Summary: Client utilities for fetching market data from Barchart
Author: nndjoli
License: MIT
Project-URL: Homepage, https://github.com/nndjoli/barchartFetcher
Classifier: Programming Language :: Python :: 3
Classifier: License :: OSI Approved :: MIT License
Classifier: Operating System :: OS Independent
Requires-Python: >=3.10
License-File: LICENSE
Requires-Dist: httpx
Requires-Dist: pandas
Requires-Dist: nest_asyncio
Requires-Dist: beautifulsoup4
Dynamic: license-file
